{
    "music_id": "2",
    "difficulty": "3",
    "notes": [{
        "id": "1",
        "time": "3539.325843",
        "type": "ka",
        "extension": "",
        "count": "",
        "bar_line": "1",
        "fever": ""
    }, {
        "id": "2",
        "time": "4887.640449",
        "type": "ka",
        "extension": "",
        "count": "",
        "bar_line": "1",
        "fever": ""
    }, {
        "id": "3",
        "time": "5393.258427",
        "type": "ka",
        "extension": "",
        "count": "",
        "bar_line": "",
        "fever": ""
    }, {
        "id": "4",
        "time": "6235.955056",
        "type": "ka",
        "extension": "",
        "count": "",
        "bar_line": "1",
        "fever": ""
    }, {
        "id": "5",
        "time": "7584.269663",
        "type": "ka",
        "extension": "",
        "count": "",
        "bar_line": "1",
        "fever": ""
    }, {
        "id": "6",
        "time": "8089.88764",
        "type": "ka",
        "extension": "",
        "count": "",
        "bar_line": "",
        "fever": ""
    }, {
        "id": "7",
        "time": "8932.58427",
        "type": "ka",
        "extension": "",
        "count": "",
        "bar_line": "1",
        "fever": ""
    }, {
        "id": "8",
        "time": "9269.662921",
        "type": "ka",
        "extension": "",
        "count": "",
        "bar_line": "",
        "fever": ""
    }, {
        "id": "9",
        "time": "9438.202247",
        "type": "ka",
        "extension": "",
        "count": "",
        "bar_line": "",
        "fever": ""
    }, {
        "id": "10",
        "time": "10280.89888",
        "type": "ka",
        "extension": "",
        "count": "",
        "bar_line": "1",
        "fever": ""
    }, {
        "id": "11",
        "time": "10617.97753",
        "type": "ka",
        "extension": "",
        "count": "",
        "bar_line": "",
        "fever": ""
    }, {
        "id": "12",
        "time": "10786.51685",
        "type": "ka",
        "extension": "",
        "count": "",
        "bar_line": "",
        "fever": ""
    }, {
        "id": "13",
        "time": "11629.21348",
        "type": "ka",
        "extension": "",
        "count": "",
        "bar_line": "1",
        "fever": ""
    }, {
        "id": "14",
        "time": "12471.91011",
        "type": "don",
        "extension": "",
        "count": "",
        "bar_line": "",
        "fever": ""
    }, {
        "id": "15",
        "time": "12640.44944",
        "type": "don",
        "extension": "",
        "count": "",
        "bar_line": "",
        "fever": ""
    }, {
        "id": "16",
        "time": "12808.98876",
        "type": "don",
        "extension": "",
        "count": "",
        "bar_line": "",
        "fever": ""
    }, {
        "id": "17",
        "time": "12977.52809",
        "type": "",
        "extension": "",
        "count": "",
        "bar_line": "1",
        "fever": ""
    }, {
        "id": "18",
        "time": "13146.06742",
        "type": "don_str",
        "extension": "",
        "count": "",
        "bar_line": "",
        "fever": ""
    }, {
        "id": "19",
        "time": "13314.60674",
        "type": "don_str",
        "extension": "",
        "count": "",
        "bar_line": "",
        "fever": ""
    }, {
        "id": "20",
        "time": "14325.8427",
        "type": "don_str",
        "extension": "",
        "count": "",
        "bar_line": "1",
        "fever": ""
    }, {
        "id": "21",
        "time": "14831.46067",
        "type": "don_str",
        "extension": "",
        "count": "",
        "bar_line": "",
        "fever": ""
    }, {
        "id": "22",
        "time": "15337.07865",
        "type": "don_str",
        "extension": "",
        "count": "",
        "bar_line": "",
        "fever": ""
    }, {
        "id": "23",
        "time": "15674.1573",
        "type": "",
        "extension": "",
        "count": "",
        "bar_line": "1",
        "fever": ""
    }, {
        "id": "24",
        "time": "15842.69663",
        "type": "don_str",
        "extension": "",
        "count": "",
        "bar_line": "",
        "fever": ""
    }, {
        "id": "25",
        "time": "16348.31461",
        "type": "don_str",
        "extension": "",
        "count": "",
        "bar_line": "",
        "fever": ""
    }, {
        "id": "26",
        "time": "16853.93258",
        "type": "kusudama",
        "extension": "18370.78652",
        "count": "13",
        "bar_line": "",
        "fever": ""
    }, {
        "id": "27",
        "time": "17022.47191",
        "type": "",
        "extension": "",
        "count": "",
        "bar_line": "1",
        "fever": ""
    }, {
        "id": "28",
        "time": "18370.78652",
        "type": "",
        "extension": "",
        "count": "",
        "bar_line": "1",
        "fever": ""
    }, {
        "id": "29",
        "time": "19719.10112",
        "type": "renda_str",
        "extension": "21741.57303",
        "count": "",
        "bar_line": "1",
        "fever": "1"
    }, {
        "id": "30",
        "time": "21067.41573",
        "type": "",
        "extension": "",
        "count": "",
        "bar_line": "1",
        "fever": ""
    }, {
        "id": "31",
        "time": "22415.73034",
        "type": "",
        "extension": "",
        "count": "",
        "bar_line": "1",
        "fever": ""
    }, {
        "id": "32",
        "time": "22752.80899",
        "type": "don_str",
        "extension": "",
        "count": "",
        "bar_line": "",
        "fever": ""
    }, {
        "id": "33",
        "time": "23426.96629",
        "type": "don_str",
        "extension": "",
        "count": "",
        "bar_line": "",
        "fever": ""
    }, {
        "id": "34",
        "time": "23764.04494",
        "type": "",
        "extension": "",
        "count": "",
        "bar_line": "1",
        "fever": ""
    }, {
        "id": "35",
        "time": "24101.1236",
        "type": "don_str",
        "extension": "",
        "count": "",
        "bar_line": "",
        "fever": ""
    }, {
        "id": "36",
        "time": "24775.2809",
        "type": "don_str",
        "extension": "",
        "count": "",
        "bar_line": "",
        "fever": ""
    }, {
        "id": "37",
        "time": "25112.35955",
        "type": "renda_str",
        "extension": "27134.83146",
        "count": "",
        "bar_line": "1",
        "fever": ""
    }, {
        "id": "38",
        "time": "26460.67416",
        "type": "",
        "extension": "",
        "count": "",
        "bar_line": "1",
        "fever": ""
    }, {
        "id": "39",
        "time": "27808.98876",
        "type": "don",
        "extension": "",
        "count": "",
        "bar_line": "1",
        "fever": ""
    }, {
        "id": "40",
        "time": "27977.52809",
        "type": "don",
        "extension": "",
        "count": "",
        "bar_line": "",
        "fever": ""
    }, {
        "id": "41",
        "time": "28146.06742",
        "type": "don",
        "extension": "",
        "count": "",
        "bar_line": "",
        "fever": ""
    }, {
        "id": "42",
        "time": "28314.60674",
        "type": "don",
        "extension": "",
        "count": "",
        "bar_line": "",
        "fever": ""
    }, {
        "id": "43",
        "time": "28483.14607",
        "type": "don",
        "extension": "",
        "count": "",
        "bar_line": "",
        "fever": ""
    }, {
        "id": "44",
        "time": "28651.68539",
        "type": "don",
        "extension": "",
        "count": "",
        "bar_line": "",
        "fever": ""
    }, {
        "id": "45",
        "time": "28820.22472",
        "type": "don",
        "extension": "",
        "count": "",
        "bar_line": "",
        "fever": ""
    }, {
        "id": "46",
        "time": "28988.76404",
        "type": "don_str",
        "extension": "",
        "count": "",
        "bar_line": "",
        "fever": ""
    }, {
        "id": "47",
        "time": "29157.30337",
        "type": "",
        "extension": "",
        "count": "",
        "bar_line": "1",
        "fever": ""
    }, {
        "id": "48",
        "time": "29325.8427",
        "type": "don_str",
        "extension": "",
        "count": "",
        "bar_line": "",
        "fever": ""
    }, {
        "id": "49",
        "time": "29494.38202",
        "type": "don_str",
        "extension": "",
        "count": "",
        "bar_line": "",
        "fever": ""
    }, {
        "id": "50",
        "time": "30505.61798",
        "type": "don",
        "extension": "",
        "count": "",
        "bar_line": "1",
        "fever": ""
    }, {
        "id": "51",
        "time": "30842.69663",
        "type": "ka",
        "extension": "",
        "count": "",
        "bar_line": "",
        "fever": ""
    }, {
        "id": "52",
        "time": "31179.77528",
        "type": "don",
        "extension": "",
        "count": "",
        "bar_line": "",
        "fever": ""
    }, {
        "id": "53",
        "time": "31853.93258",
        "type": "don",
        "extension": "",
        "count": "",
        "bar_line": "1",
        "fever": "0"
    }, {
        "id": "54",
        "time": "32191.01124",
        "type": "ka",
        "extension": "",
        "count": "",
        "bar_line": "",
        "fever": ""
    }, {
        "id": "55",
        "time": "32359.55056",
        "type": "ka",
        "extension": "",
        "count": "",
        "bar_line": "",
        "fever": ""
    }, {
        "id": "56",
        "time": "32696.62921",
        "type": "don",
        "extension": "",
        "count": "",
        "bar_line": "",
        "fever": ""
    }, {
        "id": "57",
        "time": "33033.70787",
        "type": "don",
        "extension": "",
        "count": "",
        "bar_line": "",
        "fever": ""
    }, {
        "id": "58",
        "time": "33202.24719",
        "type": "don",
        "extension": "",
        "count": "",
        "bar_line": "1",
        "fever": ""
    }, {
        "id": "59",
        "time": "33539.32584",
        "type": "ka",
        "extension": "",
        "count": "",
        "bar_line": "",
        "fever": ""
    }, {
        "id": "60",
        "time": "33707.86517",
        "type": "ka",
        "extension": "",
        "count": "",
        "bar_line": "",
        "fever": ""
    }, {
        "id": "61",
        "time": "34044.94382",
        "type": "don_str",
        "extension": "",
        "count": "",
        "bar_line": "",
        "fever": ""
    }, {
        "id": "62",
        "time": "34382.02247",
        "type": "don_str",
        "extension": "",
        "count": "",
        "bar_line": "",
        "fever": ""
    }, {
        "id": "63",
        "time": "34550.5618",
        "type": "don_str",
        "extension": "",
        "count": "",
        "bar_line": "1",
        "fever": ""
    }, {
        "id": "64",
        "time": "34887.64045",
        "type": "ka_str",
        "extension": "",
        "count": "",
        "bar_line": "",
        "fever": ""
    }, {
        "id": "65",
        "time": "35056.17978",
        "type": "ka_str",
        "extension": "",
        "count": "",
        "bar_line": "",
        "fever": ""
    }, {
        "id": "66",
        "time": "35898.8764",
        "type": "don",
        "extension": "",
        "count": "",
        "bar_line": "1",
        "fever": ""
    }, {
        "id": "67",
        "time": "36235.95506",
        "type": "ka",
        "extension": "",
        "count": "",
        "bar_line": "",
        "fever": ""
    }, {
        "id": "68",
        "time": "36573.03371",
        "type": "don",
        "extension": "",
        "count": "",
        "bar_line": "",
        "fever": ""
    }, {
        "id": "69",
        "time": "37247.19101",
        "type": "don",
        "extension": "",
        "count": "",
        "bar_line": "1",
        "fever": ""
    }, {
        "id": "70",
        "time": "37584.26966",
        "type": "ka",
        "extension": "",
        "count": "",
        "bar_line": "",
        "fever": ""
    }, {
        "id": "71",
        "time": "37752.80899",
        "type": "ka",
        "extension": "",
        "count": "",
        "bar_line": "",
        "fever": ""
    }, {
        "id": "72",
        "time": "38595.50562",
        "type": "don",
        "extension": "",
        "count": "",
        "bar_line": "1",
        "fever": ""
    }, {
        "id": "73",
        "time": "38764.04494",
        "type": "don",
        "extension": "",
        "count": "",
        "bar_line": "",
        "fever": ""
    }, {
        "id": "74",
        "time": "38932.58427",
        "type": "don",
        "extension": "",
        "count": "",
        "bar_line": "",
        "fever": ""
    }, {
        "id": "75",
        "time": "39269.66292",
        "type": "ka",
        "extension": "",
        "count": "",
        "bar_line": "",
        "fever": ""
    }, {
        "id": "76",
        "time": "39438.20225",
        "type": "ka",
        "extension": "",
        "count": "",
        "bar_line": "",
        "fever": ""
    }, {
        "id": "77",
        "time": "39606.74157",
        "type": "ka",
        "extension": "",
        "count": "",
        "bar_line": "",
        "fever": ""
    }, {
        "id": "78",
        "time": "39943.82022",
        "type": "don_str",
        "extension": "",
        "count": "",
        "bar_line": "1",
        "fever": ""
    }, {
        "id": "79",
        "time": "40449.4382",
        "type": "don_str",
        "extension": "",
        "count": "",
        "bar_line": "",
        "fever": ""
    }, {
        "id": "80",
        "time": "41292.13483",
        "type": "don",
        "extension": "",
        "count": "",
        "bar_line": "1",
        "fever": ""
    }, {
        "id": "81",
        "time": "41629.21348",
        "type": "ka",
        "extension": "",
        "count": "",
        "bar_line": "",
        "fever": ""
    }, {
        "id": "82",
        "time": "41797.75281",
        "type": "don",
        "extension": "",
        "count": "",
        "bar_line": "",
        "fever": ""
    }, {
        "id": "83",
        "time": "41966.29213",
        "type": "don",
        "extension": "",
        "count": "",
        "bar_line": "",
        "fever": ""
    }, {
        "id": "84",
        "time": "42471.91011",
        "type": "don",
        "extension": "",
        "count": "",
        "bar_line": "",
        "fever": ""
    }, {
        "id": "85",
        "time": "42640.44944",
        "type": "don",
        "extension": "",
        "count": "",
        "bar_line": "1",
        "fever": ""
    }, {
        "id": "86",
        "time": "42977.52809",
        "type": "ka",
        "extension": "",
        "count": "",
        "bar_line": "",
        "fever": ""
    }, {
        "id": "87",
        "time": "43146.06742",
        "type": "ka",
        "extension": "",
        "count": "",
        "bar_line": "",
        "fever": ""
    }, {
        "id": "88",
        "time": "43314.60674",
        "type": "don",
        "extension": "",
        "count": "",
        "bar_line": "",
        "fever": ""
    }, {
        "id": "89",
        "time": "43483.14607",
        "type": "don",
        "extension": "",
        "count": "",
        "bar_line": "",
        "fever": ""
    }, {
        "id": "90",
        "time": "43820.22472",
        "type": "don",
        "extension": "",
        "count": "",
        "bar_line": "",
        "fever": ""
    }, {
        "id": "91",
        "time": "43988.76404",
        "type": "don",
        "extension": "",
        "count": "",
        "bar_line": "1",
        "fever": ""
    }, {
        "id": "92",
        "time": "44325.8427",
        "type": "ka",
        "extension": "",
        "count": "",
        "bar_line": "",
        "fever": ""
    }, {
        "id": "93",
        "time": "44494.38202",
        "type": "ka",
        "extension": "",
        "count": "",
        "bar_line": "",
        "fever": ""
    }, {
        "id": "94",
        "time": "44831.46067",
        "type": "don",
        "extension": "",
        "count": "",
        "bar_line": "",
        "fever": ""
    }, {
        "id": "95",
        "time": "45000",
        "type": "don",
        "extension": "",
        "count": "",
        "bar_line": "",
        "fever": ""
    }, {
        "id": "96",
        "time": "45168.53933",
        "type": "don",
        "extension": "",
        "count": "",
        "bar_line": "",
        "fever": ""
    }, {
        "id": "97",
        "time": "45337.07865",
        "type": "",
        "extension": "",
        "count": "",
        "bar_line": "1",
        "fever": ""
    }, {
        "id": "98",
        "time": "45505.61798",
        "type": "ka",
        "extension": "",
        "count": "",
        "bar_line": "",
        "fever": ""
    }, {
        "id": "99",
        "time": "45674.1573",
        "type": "ka",
        "extension": "",
        "count": "",
        "bar_line": "",
        "fever": ""
    }, {
        "id": "100",
        "time": "45842.69663",
        "type": "ka",
        "extension": "",
        "count": "",
        "bar_line": "",
        "fever": ""
    }, {
        "id": "101",
        "time": "46011.23596",
        "type": "don",
        "extension": "",
        "count": "",
        "bar_line": "",
        "fever": ""
    }, {
        "id": "102",
        "time": "46179.77528",
        "type": "don",
        "extension": "",
        "count": "",
        "bar_line": "",
        "fever": ""
    }, {
        "id": "103",
        "time": "46348.31461",
        "type": "don",
        "extension": "",
        "count": "",
        "bar_line": "",
        "fever": ""
    }, {
        "id": "104",
        "time": "46685.39326",
        "type": "ka_str",
        "extension": "",
        "count": "",
        "bar_line": "1",
        "fever": ""
    }, {
        "id": "105",
        "time": "47022.47191",
        "type": "ka_str",
        "extension": "",
        "count": "",
        "bar_line": "",
        "fever": ""
    }, {
        "id": "106",
        "time": "47191.01124",
        "type": "ka_str",
        "extension": "",
        "count": "",
        "bar_line": "",
        "fever": ""
    }, {
        "id": "107",
        "time": "47865.16854",
        "type": "don_str",
        "extension": "",
        "count": "",
        "bar_line": "",
        "fever": ""
    }, {
        "id": "108",
        "time": "48033.70787",
        "type": "don_str",
        "extension": "",
        "count": "",
        "bar_line": "1",
        "fever": ""
    }, {
        "id": "109",
        "time": "48370.78652",
        "type": "don_str",
        "extension": "",
        "count": "",
        "bar_line": "",
        "fever": ""
    }, {
        "id": "110",
        "time": "48539.32584",
        "type": "don_str",
        "extension": "",
        "count": "",
        "bar_line": "",
        "fever": ""
    }, {
        "id": "111",
        "time": "49044.94382",
        "type": "don",
        "extension": "",
        "count": "",
        "bar_line": "",
        "fever": ""
    }, {
        "id": "112",
        "time": "49213.48315",
        "type": "don",
        "extension": "",
        "count": "",
        "bar_line": "",
        "fever": ""
    }, {
        "id": "113",
        "time": "49382.02247",
        "type": "don",
        "extension": "",
        "count": "",
        "bar_line": "1",
        "fever": ""
    }, {
        "id": "114",
        "time": "49719.10112",
        "type": "don",
        "extension": "",
        "count": "",
        "bar_line": "",
        "fever": ""
    }, {
        "id": "115",
        "time": "50056.17978",
        "type": "don",
        "extension": "",
        "count": "",
        "bar_line": "",
        "fever": ""
    }, {
        "id": "116",
        "time": "50224.7191",
        "type": "don",
        "extension": "",
        "count": "",
        "bar_line": "",
        "fever": ""
    }, {
        "id": "117",
        "time": "50393.25843",
        "type": "don",
        "extension": "",
        "count": "",
        "bar_line": "",
        "fever": ""
    }, {
        "id": "118",
        "time": "50561.79775",
        "type": "balloon",
        "extension": "51404.49438",
        "count": "7",
        "bar_line": "",
        "fever": ""
    }, {
        "id": "119",
        "time": "50730.33708",
        "type": "",
        "extension": "",
        "count": "",
        "bar_line": "1",
        "fever": ""
    }, {
        "id": "120",
        "time": "52078.65169",
        "type": "renda",
        "extension": "52752.80899",
        "count": "",
        "bar_line": "1",
        "fever": ""
    }, {
        "id": "121",
        "time": "53089.88764",
        "type": "ka_str",
        "extension": "",
        "count": "",
        "bar_line": "",
        "fever": ""
    }, {
        "id": "122",
        "time": "53426.96629",
        "type": "renda",
        "extension": "54101.1236",
        "count": "",
        "bar_line": "1",
        "fever": ""
    }, {
        "id": "123",
        "time": "54438.20225",
        "type": "ka_str",
        "extension": "",
        "count": "",
        "bar_line": "",
        "fever": ""
    }, {
        "id": "124",
        "time": "54775.2809",
        "type": "renda",
        "extension": "55449.4382",
        "count": "",
        "bar_line": "1",
        "fever": ""
    }, {
        "id": "125",
        "time": "55786.51685",
        "type": "ka_str",
        "extension": "",
        "count": "",
        "bar_line": "",
        "fever": ""
    }, {
        "id": "126",
        "time": "56123.59551",
        "type": "renda",
        "extension": "56797.75281",
        "count": "",
        "bar_line": "1",
        "fever": ""
    }, {
        "id": "127",
        "time": "56966.29213",
        "type": "don",
        "extension": "",
        "count": "",
        "bar_line": "",
        "fever": ""
    }, {
        "id": "128",
        "time": "57134.83146",
        "type": "ka",
        "extension": "",
        "count": "",
        "bar_line": "",
        "fever": ""
    }, {
        "id": "129",
        "time": "57303.37079",
        "type": "don",
        "extension": "",
        "count": "",
        "bar_line": "",
        "fever": ""
    }, {
        "id": "130",
        "time": "57471.91011",
        "type": "",
        "extension": "",
        "count": "",
        "bar_line": "1",
        "fever": ""
    }, {
        "id": "131",
        "time": "57640.44944",
        "type": "don",
        "extension": "",
        "count": "",
        "bar_line": "",
        "fever": ""
    }, {
        "id": "132",
        "time": "57808.98876",
        "type": "ka",
        "extension": "",
        "count": "",
        "bar_line": "",
        "fever": ""
    }, {
        "id": "133",
        "time": "57977.52809",
        "type": "ka",
        "extension": "",
        "count": "",
        "bar_line": "",
        "fever": ""
    }, {
        "id": "134",
        "time": "58146.06742",
        "type": "don",
        "extension": "",
        "count": "",
        "bar_line": "",
        "fever": ""
    }, {
        "id": "135",
        "time": "58483.14607",
        "type": "ka",
        "extension": "",
        "count": "",
        "bar_line": "",
        "fever": ""
    }, {
        "id": "136",
        "time": "58651.68539",
        "type": "don",
        "extension": "",
        "count": "",
        "bar_line": "",
        "fever": ""
    }, {
        "id": "137",
        "time": "58820.22472",
        "type": "",
        "extension": "",
        "count": "",
        "bar_line": "1",
        "fever": ""
    }, {
        "id": "138",
        "time": "58988.76404",
        "type": "don",
        "extension": "",
        "count": "",
        "bar_line": "",
        "fever": ""
    }, {
        "id": "139",
        "time": "59157.30337",
        "type": "ka",
        "extension": "",
        "count": "",
        "bar_line": "",
        "fever": ""
    }, {
        "id": "140",
        "time": "59325.8427",
        "type": "ka",
        "extension": "",
        "count": "",
        "bar_line": "",
        "fever": ""
    }, {
        "id": "141",
        "time": "59494.38202",
        "type": "don",
        "extension": "",
        "count": "",
        "bar_line": "",
        "fever": ""
    }, {
        "id": "142",
        "time": "59662.92135",
        "type": "don",
        "extension": "",
        "count": "",
        "bar_line": "",
        "fever": ""
    }, {
        "id": "143",
        "time": "60000",
        "type": "don",
        "extension": "",
        "count": "",
        "bar_line": "",
        "fever": ""
    }, {
        "id": "144",
        "time": "60168.53933",
        "type": "",
        "extension": "",
        "count": "",
        "bar_line": "1",
        "fever": ""
    }, {
        "id": "145",
        "time": "60337.07865",
        "type": "don",
        "extension": "",
        "count": "",
        "bar_line": "",
        "fever": ""
    }, {
        "id": "146",
        "time": "60505.61798",
        "type": "ka",
        "extension": "",
        "count": "",
        "bar_line": "",
        "fever": ""
    }, {
        "id": "147",
        "time": "60674.1573",
        "type": "ka",
        "extension": "",
        "count": "",
        "bar_line": "",
        "fever": ""
    }, {
        "id": "148",
        "time": "60842.69663",
        "type": "don",
        "extension": "",
        "count": "",
        "bar_line": "",
        "fever": ""
    }, {
        "id": "149",
        "time": "61011.23596",
        "type": "don",
        "extension": "",
        "count": "",
        "bar_line": "",
        "fever": ""
    }, {
        "id": "150",
        "time": "61348.31461",
        "type": "don",
        "extension": "",
        "count": "",
        "bar_line": "",
        "fever": ""
    }, {
        "id": "151",
        "time": "61516.85393",
        "type": "ka",
        "extension": "",
        "count": "",
        "bar_line": "1",
        "fever": ""
    }, {
        "id": "152",
        "time": "61853.93258",
        "type": "ka",
        "extension": "",
        "count": "",
        "bar_line": "",
        "fever": ""
    }, {
        "id": "153",
        "time": "62191.01124",
        "type": "renda_str",
        "extension": "63876.40449",
        "count": "",
        "bar_line": "",
        "fever": ""
    }, {
        "id": "154",
        "time": "62865.16854",
        "type": "",
        "extension": "",
        "count": "",
        "bar_line": "1",
        "fever": ""
    }, {
        "id": "155",
        "time": "64213.48315",
        "type": "ka_str",
        "extension": "",
        "count": "",
        "bar_line": "1",
        "fever": ""
    }, {
        "id": "156",
        "time": "64382.02247",
        "type": "ka_str",
        "extension": "",
        "count": "",
        "bar_line": "",
        "fever": ""
    }, {
        "id": "157",
        "time": "64550.5618",
        "type": "ka_str",
        "extension": "",
        "count": "",
        "bar_line": "",
        "fever": ""
    }, {
        "id": "158",
        "time": "64887.64045",
        "type": "don_str",
        "extension": "",
        "count": "",
        "bar_line": "",
        "fever": ""
    }, {
        "id": "159",
        "time": "65224.7191",
        "type": "don_str",
        "extension": "",
        "count": "",
        "bar_line": "",
        "fever": ""
    }, {
        "id": "160",
        "time": "65561.79775",
        "type": "don_str",
        "extension": "",
        "count": "",
        "bar_line": "1",
        "fever": "1"
    }, {
        "id": "161",
        "time": "65898.8764",
        "type": "ka",
        "extension": "",
        "count": "",
        "bar_line": "",
        "fever": ""
    }, {
        "id": "162",
        "time": "66235.95506",
        "type": "don",
        "extension": "",
        "count": "",
        "bar_line": "",
        "fever": ""
    }, {
        "id": "163",
        "time": "66404.49438",
        "type": "don",
        "extension": "",
        "count": "",
        "bar_line": "",
        "fever": ""
    }, {
        "id": "164",
        "time": "66573.03371",
        "type": "ka",
        "extension": "",
        "count": "",
        "bar_line": "",
        "fever": ""
    }, {
        "id": "165",
        "time": "66741.57303",
        "type": "don",
        "extension": "",
        "count": "",
        "bar_line": "",
        "fever": ""
    }, {
        "id": "166",
        "time": "66910.11236",
        "type": "",
        "extension": "",
        "count": "",
        "bar_line": "1",
        "fever": ""
    }, {
        "id": "167",
        "time": "67247.19101",
        "type": "ka",
        "extension": "",
        "count": "",
        "bar_line": "",
        "fever": ""
    }, {
        "id": "168",
        "time": "67415.73034",
        "type": "don",
        "extension": "",
        "count": "",
        "bar_line": "",
        "fever": ""
    }, {
        "id": "169",
        "time": "67752.80899",
        "type": "don",
        "extension": "",
        "count": "",
        "bar_line": "",
        "fever": ""
    }, {
        "id": "170",
        "time": "67921.34831",
        "type": "ka",
        "extension": "",
        "count": "",
        "bar_line": "",
        "fever": ""
    }, {
        "id": "171",
        "time": "68258.42697",
        "type": "don",
        "extension": "",
        "count": "",
        "bar_line": "1",
        "fever": ""
    }, {
        "id": "172",
        "time": "68595.50562",
        "type": "ka",
        "extension": "",
        "count": "",
        "bar_line": "",
        "fever": ""
    }, {
        "id": "173",
        "time": "68932.58427",
        "type": "don",
        "extension": "",
        "count": "",
        "bar_line": "",
        "fever": ""
    }, {
        "id": "174",
        "time": "69101.1236",
        "type": "don",
        "extension": "",
        "count": "",
        "bar_line": "",
        "fever": ""
    }, {
        "id": "175",
        "time": "69269.66292",
        "type": "ka",
        "extension": "",
        "count": "",
        "bar_line": "",
        "fever": ""
    }, {
        "id": "176",
        "time": "69606.74157",
        "type": "don_str",
        "extension": "",
        "count": "",
        "bar_line": "1",
        "fever": ""
    }, {
        "id": "177",
        "time": "70112.35955",
        "type": "don_str",
        "extension": "",
        "count": "",
        "bar_line": "",
        "fever": ""
    }, {
        "id": "178",
        "time": "70955.05618",
        "type": "don",
        "extension": "",
        "count": "",
        "bar_line": "1",
        "fever": ""
    }, {
        "id": "179",
        "time": "71123.59551",
        "type": "don",
        "extension": "",
        "count": "",
        "bar_line": "",
        "fever": ""
    }, {
        "id": "180",
        "time": "71292.13483",
        "type": "don",
        "extension": "",
        "count": "",
        "bar_line": "",
        "fever": ""
    }, {
        "id": "181",
        "time": "71460.67416",
        "type": "don",
        "extension": "",
        "count": "",
        "bar_line": "",
        "fever": ""
    }, {
        "id": "182",
        "time": "71797.75281",
        "type": "don",
        "extension": "",
        "count": "",
        "bar_line": "",
        "fever": ""
    }, {
        "id": "183",
        "time": "71966.29213",
        "type": "don",
        "extension": "",
        "count": "",
        "bar_line": "",
        "fever": ""
    }, {
        "id": "184",
        "time": "72134.83146",
        "type": "don",
        "extension": "",
        "count": "",
        "bar_line": "",
        "fever": ""
    }, {
        "id": "185",
        "time": "72303.37079",
        "type": "",
        "extension": "",
        "count": "",
        "bar_line": "1",
        "fever": ""
    }, {
        "id": "186",
        "time": "72471.91011",
        "type": "don",
        "extension": "",
        "count": "",
        "bar_line": "",
        "fever": ""
    }, {
        "id": "187",
        "time": "72640.44944",
        "type": "don",
        "extension": "",
        "count": "",
        "bar_line": "",
        "fever": ""
    }, {
        "id": "188",
        "time": "72808.98876",
        "type": "don",
        "extension": "",
        "count": "",
        "bar_line": "",
        "fever": ""
    }, {
        "id": "189",
        "time": "73483.14607",
        "type": "ka",
        "extension": "",
        "count": "",
        "bar_line": "",
        "fever": ""
    }, {
        "id": "190",
        "time": "73651.68539",
        "type": "",
        "extension": "",
        "count": "",
        "bar_line": "1",
        "fever": ""
    }, {
        "id": "191",
        "time": "73820.22472",
        "type": "ka",
        "extension": "",
        "count": "",
        "bar_line": "",
        "fever": ""
    }, {
        "id": "192",
        "time": "73988.76404",
        "type": "ka",
        "extension": "",
        "count": "",
        "bar_line": "",
        "fever": ""
    }, {
        "id": "193",
        "time": "74157.30337",
        "type": "ka",
        "extension": "",
        "count": "",
        "bar_line": "",
        "fever": ""
    }, {
        "id": "194",
        "time": "74325.8427",
        "type": "ka",
        "extension": "",
        "count": "",
        "bar_line": "",
        "fever": ""
    }, {
        "id": "195",
        "time": "74494.38202",
        "type": "ka",
        "extension": "",
        "count": "",
        "bar_line": "",
        "fever": ""
    }, {
        "id": "196",
        "time": "74831.46067",
        "type": "ka_str",
        "extension": "",
        "count": "",
        "bar_line": "",
        "fever": ""
    }, {
        "id": "197",
        "time": "75000",
        "type": "",
        "extension": "",
        "count": "",
        "bar_line": "1",
        "fever": ""
    }, {
        "id": "198",
        "time": "75674.1573",
        "type": "don_str",
        "extension": "",
        "count": "",
        "bar_line": "",
        "fever": ""
    }, {
        "id": "199",
        "time": "76011.23596",
        "type": "don_str",
        "extension": "",
        "count": "",
        "bar_line": "",
        "fever": ""
    }, {
        "id": "200",
        "time": "76348.31461",
        "type": "don_str",
        "extension": "",
        "count": "",
        "bar_line": "1",
        "fever": ""
    }, {
        "id": "201",
        "time": "76685.39326",
        "type": "ka",
        "extension": "",
        "count": "",
        "bar_line": "",
        "fever": ""
    }, {
        "id": "202",
        "time": "77022.47191",
        "type": "don",
        "extension": "",
        "count": "",
        "bar_line": "",
        "fever": ""
    }, {
        "id": "203",
        "time": "77191.01124",
        "type": "don",
        "extension": "",
        "count": "",
        "bar_line": "",
        "fever": ""
    }, {
        "id": "204",
        "time": "77359.55056",
        "type": "ka",
        "extension": "",
        "count": "",
        "bar_line": "",
        "fever": ""
    }, {
        "id": "205",
        "time": "77528.08989",
        "type": "don",
        "extension": "",
        "count": "",
        "bar_line": "",
        "fever": ""
    }, {
        "id": "206",
        "time": "77696.62921",
        "type": "",
        "extension": "",
        "count": "",
        "bar_line": "1",
        "fever": ""
    }, {
        "id": "207",
        "time": "78033.70787",
        "type": "ka",
        "extension": "",
        "count": "",
        "bar_line": "",
        "fever": ""
    }, {
        "id": "208",
        "time": "78202.24719",
        "type": "don",
        "extension": "",
        "count": "",
        "bar_line": "",
        "fever": ""
    }, {
        "id": "209",
        "time": "78539.32584",
        "type": "don",
        "extension": "",
        "count": "",
        "bar_line": "",
        "fever": ""
    }, {
        "id": "210",
        "time": "78707.86517",
        "type": "ka",
        "extension": "",
        "count": "",
        "bar_line": "",
        "fever": ""
    }, {
        "id": "211",
        "time": "79044.94382",
        "type": "don",
        "extension": "",
        "count": "",
        "bar_line": "1",
        "fever": ""
    }, {
        "id": "212",
        "time": "79382.02247",
        "type": "ka",
        "extension": "",
        "count": "",
        "bar_line": "",
        "fever": ""
    }, {
        "id": "213",
        "time": "79719.10112",
        "type": "don",
        "extension": "",
        "count": "",
        "bar_line": "",
        "fever": ""
    }, {
        "id": "214",
        "time": "79887.64045",
        "type": "don",
        "extension": "",
        "count": "",
        "bar_line": "",
        "fever": ""
    }, {
        "id": "215",
        "time": "80056.17978",
        "type": "don",
        "extension": "",
        "count": "",
        "bar_line": "",
        "fever": ""
    }, {
        "id": "216",
        "time": "80224.7191",
        "type": "ka",
        "extension": "",
        "count": "",
        "bar_line": "",
        "fever": ""
    }, {
        "id": "217",
        "time": "80393.25843",
        "type": "",
        "extension": "",
        "count": "",
        "bar_line": "1",
        "fever": ""
    }, {
        "id": "218",
        "time": "80561.79775",
        "type": "ka",
        "extension": "",
        "count": "",
        "bar_line": "",
        "fever": ""
    }, {
        "id": "219",
        "time": "80730.33708",
        "type": "don",
        "extension": "",
        "count": "",
        "bar_line": "",
        "fever": ""
    }, {
        "id": "220",
        "time": "80898.8764",
        "type": "don",
        "extension": "",
        "count": "",
        "bar_line": "",
        "fever": ""
    }, {
        "id": "221",
        "time": "81741.57303",
        "type": "don",
        "extension": "",
        "count": "",
        "bar_line": "1",
        "fever": ""
    }, {
        "id": "222",
        "time": "81910.11236",
        "type": "don",
        "extension": "",
        "count": "",
        "bar_line": "",
        "fever": ""
    }, {
        "id": "223",
        "time": "82078.65169",
        "type": "don",
        "extension": "",
        "count": "",
        "bar_line": "",
        "fever": ""
    }, {
        "id": "224",
        "time": "82247.19101",
        "type": "don",
        "extension": "",
        "count": "",
        "bar_line": "",
        "fever": ""
    }, {
        "id": "225",
        "time": "82584.26966",
        "type": "don",
        "extension": "",
        "count": "",
        "bar_line": "",
        "fever": ""
    }, {
        "id": "226",
        "time": "82752.80899",
        "type": "don",
        "extension": "",
        "count": "",
        "bar_line": "",
        "fever": ""
    }, {
        "id": "227",
        "time": "82921.34831",
        "type": "don",
        "extension": "",
        "count": "",
        "bar_line": "",
        "fever": ""
    }, {
        "id": "228",
        "time": "83089.88764",
        "type": "",
        "extension": "",
        "count": "",
        "bar_line": "1",
        "fever": ""
    }, {
        "id": "229",
        "time": "83258.42697",
        "type": "don",
        "extension": "",
        "count": "",
        "bar_line": "",
        "fever": ""
    }, {
        "id": "230",
        "time": "83426.96629",
        "type": "don",
        "extension": "",
        "count": "",
        "bar_line": "",
        "fever": ""
    }, {
        "id": "231",
        "time": "83595.50562",
        "type": "don",
        "extension": "",
        "count": "",
        "bar_line": "",
        "fever": ""
    }, {
        "id": "232",
        "time": "84101.1236",
        "type": "ka",
        "extension": "",
        "count": "",
        "bar_line": "",
        "fever": ""
    }, {
        "id": "233",
        "time": "84438.20225",
        "type": "ka",
        "extension": "",
        "count": "",
        "bar_line": "1",
        "fever": ""
    }, {
        "id": "234",
        "time": "84775.2809",
        "type": "ka",
        "extension": "",
        "count": "",
        "bar_line": "",
        "fever": ""
    }, {
        "id": "235",
        "time": "85112.35955",
        "type": "don",
        "extension": "",
        "count": "",
        "bar_line": "",
        "fever": ""
    }, {
        "id": "236",
        "time": "85280.89888",
        "type": "don",
        "extension": "",
        "count": "",
        "bar_line": "",
        "fever": ""
    }, {
        "id": "237",
        "time": "85449.4382",
        "type": "don",
        "extension": "",
        "count": "",
        "bar_line": "",
        "fever": ""
    }, {
        "id": "238",
        "time": "85617.97753",
        "type": "don_str",
        "extension": "",
        "count": "",
        "bar_line": "",
        "fever": ""
    }, {
        "id": "239",
        "time": "85786.51685",
        "type": "",
        "extension": "",
        "count": "",
        "bar_line": "1",
        "fever": ""
    }, {
        "id": "240",
        "time": "85955.05618",
        "type": "don_str",
        "extension": "",
        "count": "",
        "bar_line": "",
        "fever": ""
    }, {
        "id": "241",
        "time": "86123.59551",
        "type": "don_str",
        "extension": "",
        "count": "",
        "bar_line": "",
        "fever": ""
    }, {
        "id": "242",
        "time": "86797.75281",
        "type": "ka_str",
        "extension": "",
        "count": "",
        "bar_line": "",
        "fever": ""
    }, {
        "id": "243",
        "time": "87134.83146",
        "type": "renda_str",
        "extension": "89325.8427",
        "count": "",
        "bar_line": "1",
        "fever": ""
    }, {
        "id": "244",
        "time": "88483.14607",
        "type": "",
        "extension": "",
        "count": "",
        "bar_line": "1",
        "fever": ""
    }, {
        "id": "245",
        "time": "89662.92135",
        "type": "don_str",
        "extension": "",
        "count": "",
        "bar_line": "",
        "fever": ""
    }, {
        "id": "246",
        "time": "89831.46067",
        "type": "",
        "extension": "",
        "count": "",
        "bar_line": "1",
        "fever": "0"
    }, {
        "id": "247",
        "time": "91179.77528",
        "type": "",
        "extension": "",
        "count": "",
        "bar_line": "1",
        "fever": ""
    }]
}